{
    "Búsquedas": "Búsquedas",
    "Accesos": "Accesos",
    "Actualizaciones": "Actualizaciones",
    "Eliminaciones": "Eliminaciones",
    "Asunto": "Asunto",
    "Dirección": "Dirección",
    "Código postal": "Código postal",
    "Información adicional (opcional)": "Información adicional (opcional)",
    "Envíar": "Enviar",
    "Déjanos saber lo que necesitas y nosotros nos encargaremos del resto": "Déjanos saber lo que necesitas y nosotros nos encargaremos del resto",
    "Acceso rápido": "Acceso rápido",
    "Mis cotizaciones": "Mis cotizaciones",
    "Actividad": "Actividad",
    "Catálogos": "Catálogos",
    "Servicio al Consumidor": "Servicio al Consumidor",
    "Chat en línea": "Chat en línea",
    "Enviar un correo electrónico": "Enviar un correo electrónico",
    "Inbox": "Bandeja de entrada",
    "Síguenos": "Síguenos",
    "Instagram": "Instagram",
    "Facebook": "Facebook",
    "YouTube": "YouTube",
    "LinkedIn": "LinkedIn",
    "Ser visto": "Ser visto",
    "GENERA TU COTIZACIÓN": "GENERAR TU COTIZACIÓN",
    "Kalstein. Todos los derechos reservados.": "Kalstein. Todos los derechos reservados.",
    "Cotizaciones procesadas": "Cotizaciones procesadas",
    "Cotizaciones pendientes": "Cotizaciones pendientes",
    "Cotizaciones totales": "Cotizaciones totales",
    "Completa perfil de usuario": "Completa perfil de usuario",
    "Añadir cumpleaños": "Añadir cumpleaños",
    "Añadir nombre de compañía": "Añadir nombre de compañía",
    "Añadir foto de documento de identidad": "Añadir foto de documento de identidad",
    "Añadir número de documento": "Añadir número de documento",
    "Foto del documento legal de compañía": "Foto del documento legal de compañía",
    "Añadir documento legal de compañía": "Añadir documento legal de compañía",
    "Añadir rol de compañía": "Añadir rol de compañía",
    "Añadir dirección de compañía": "Añadir dirección de compañía",
    "Añadir país de companía": "Añadir país de compañía",
    "Añadir ciudad de compañía": "Añadir ciudad de compañía",
    "Añadir código postal de compañía": "Añadir código postal de compañía",
    "Añadir teléfono de compañía": "Añadir teléfono de compañía",
    "Añadir sitio web de compañía": "Añadir sitio web de compañía",
    "Añadir imagen de perfíl": "Añadir imagen de perfil",
    "¡Felicidades, tu perfil está completo!": "¡Felicidades, tu perfil está completo!",
    "Resumen de cotizaciones": "Resumen de cotizaciones",
    "Establecer por defecto las opciones a seleccionar en las cotizaciones acelera un poco más el proceso de generación de cotizaciones.": "Establecer por defecto las opciones a seleccionar en las cotizaciones acelera un poco más el proceso de generación de cotizaciones.",
    "¡Configura aquí!": "¡Configura aquí!",
    "Configura tus metodos de cotización": "Configura tus métodos de cotización",
    "Cotizaciones recientes": "Cotizaciones recientes",
    "Solo las 10 más recientes": "Solo las 10 más recientes",
    "Ver más": "Ver más",
    "Búsquedas recientes": "Búsquedas recientes",
    "Solo las 10 más recientes.": "Solo las 10 más recientes.",
    "Soporte técnico": "Soporte técnico",
    "Diagnóstico": "Diagnóstico",
    "Todo": "Todo",
    "Historial": "Historial",
    "Configuración": "Configuración",
    "Productos recientemente cotizados": "Productos recientemente cotizados",
    "De": "De",
    "Para": "Para",
    "Estatus": "Estatus",
    "Selecciona": "Selecciona",
    "Pendiente": "Pendiente",
    "Procesar": "Procesar",
    "Cancelar": "Cancelar",
    "Procesado": "Procesado",
    "Cancelado": "Cancelado",
    "Buscar": "Buscar",
    "Detalles de pago": "Detalles de pago",
    "Almacén": "Almacén",
    "Seleccionar": "Seleccionar",
    "Moneda": "Moneda",
    "Método de pago": "Método de pago",
    "Transferencia bancaria": "Transferencia bancaria",
    "Credito/Tarjeta de débito (Pasarela de pago)": "Crédito/Tarjeta de débito (Pasarela de pago)",
    "Detalles de destino": "Detalles de destino",
    "Método de envio": "Método de envío",
    "Aéreo": "Aéreo",
    "Marítimo": "Marítimo",
    "días": "días",
    "Destino": "Destino",
    "Código ZIP": "Código ZIP",
    "Guardar cambios": "Guardar cambios",
    "Título del modal": "Título del modal",
    "Cerrar": "Cerrar",
    "Buscar un agente de soporte": "Buscar un agente de soporte",
    "Historia": "Historia",
    "Orden de Servicio": "Orden de Servicio",
    "Buscar el servicio de su requerimiento": "Buscar el servicio de su requerimiento",
    "Modelo del Producto:": "Modelo del Producto:",
    "Modelo de Equipo": "Modelo de Equipo",
    "Escribe la aplicación:": "Escribe la aplicación:",
    "Nivel de Exigencia:": "Nivel de Exigencia:",
    "Elige una opción": "Elige una opción",
    "Bajo": "Bajo",
    "Media": "Media",
    "Alto": "Alto",
    "Generar Ticket": "Generar Ticket",
    "Perfil": "Perfil",
    "Identificaciones": "Identificaciones",
    "Seguridad": "Seguridad",
    "Foto de perfil": "Foto de perfil",
    "Subir una nueva imágen": "Subir una nueva imagen",
    "Detalles de la cuenta": "Detalles de la cuenta",
    "Dirección de correo electrónico": "Dirección de correo electrónico",
    "Ingresa tu dirección de correo electrónico": "Ingresa tu dirección de correo electrónico",
    "Primer nombre": "Primer nombre",
    "Ingresa tu primer nombre": "Ingresa tu primer nombre",
    "Segundo nombre": "Segundo nombre",
    "Ingresa tu segundo nombre": "Ingresa tu segundo nombre",
    "País": "País",
    "Ejemplo de select por defecto": "Ejemplo de select por defecto",
    "Estado": "Estado",
    "Ingresa tu Estado": "Ingresa tu Estado",
    "Ingresa tu dirección": "Ingresa tu dirección",
    "Ingresa tu código ZIP": "Ingresa tu código ZIP",
    "Número de teléfono": "Número de teléfono",
    "Ingresa tu número de teléfono": "Ingresa tu número de teléfono",
    "Cumpleaños": "Cumpleaños",
    "Ingresa tu cumpleaños": "Ingresa tu cumpleaños",
    "Detalles de la Organización": "Detalles de la Organización",
    "Nommbre de la Organización": "Nombre de la Organización",
    "Ingresa el nombre de tu organización": "Ingresa el nombre de tu organización",
    "Rol de empleo": "Rol de empleo",
    "Ingeniero": "Ingeniero",
    "Gestión de Ingeniería": "Gestión de Ingeniería",
    "Diseñador": "Diseñador",
    "Compras / Comprador / Finanzas": "Compras / Comprador / Finanzas",
    "Programa / Gestión de proyecto": "Programa / Gestión de proyecto",
    "Operaciones / Gestión MRO": "Operaciones / Gestión MRO",
    "Liderazgo ejecutivo (CXO, VP, fundador, etc.)": "Liderazgo ejecutivo (CXO, VP, fundador, etc.)",
    "Ventas y Marketing": "Ventas y Marketing",
    "Otros": "Otros",
    "Ingresa el Estado de tu organización": "Ingresa el Estado de tu organización",
    "Ingresa la dirección de tu Organización": "Ingresa la dirección de tu Organización",
    "Ingresa el código ZIP de tu organización": "Ingresa el código ZIP de tu organización",
    "Ingresa el número de teléfono de tu Organización": "Ingresa el número de teléfono de tu Organización",
    "URL de sitio web": "URL de sitio web",
    "Ingresa el sitio Web de tu Organización": "Ingresa el sitio Web de tu Organización",
    "Cambiar contraseña": "Cambiar contraseña",
    "Contraseña actual": "Contraseña actual",
    "Ingresa la contraseña actual": "Ingresa la contraseña actual",
    "Nueva contreseña": "Nueva contraseña",
    "Ingresa una nueva contraseña": "Ingresa una nueva contraseña",
    "Confirmar contraseña": "Confirmar contraseña",
    "Confirmar nueva contraseña": "Confirmar nueva contraseña",
    "Guardar": "Guardar",
    "Borrar cuenta": "Borrar cuenta",
    "Eliminar su cuenta es una acción permanente y no se puede deshacer. Si estás seguro de que Si desea eliminar su cuenta, seleccione el botón a continuación.": "Eliminar su cuenta es una acción permanente y no se puede deshacer. Si estás seguro de que Si desea eliminar su cuenta, seleccione el botón a continuación.",
    "Entiendo, borrar cuenta": "Entiendo, borrar cuenta",
    "Tarjeta de identificación": "Tarjeta de identificación",
    "Documento fiscal": "Documento fiscal",
    "Condición": "Condición",
    "Empresa": "Empresa",
    "Fabricante": "Fabricante",
    "Modelo": "Modelo",
    "-18% de descuento con pre-orden": "-18% de descuento con pre-orden",
    "Cantidad:": "Cantidad:",
    "Cotizar": "Cotizar",
    "Accesorios adicionales": "Accesorios adicionales",
    "Ver": "Ver",
    "Descripción de producto": "Descripción de producto",
    "Error": "Error",
    "Pago": "Pago",
    "rechazado": "rechazado",
    "cancelado": "cancelado",
    "Pago rechazado o cancelado.": "Pago rechazado o cancelado.",
    "Lo sentimos, ha ocurrido un problema con su pago.": "Lo sentimos, ha ocurrido un problema con su pago.",
    "Volver a la Plataforma": "Volver a la Plataforma",
    "¡El producto ya ha sido registrado por otro cliente!": "¡El producto ya ha sido registrado por otro cliente!",
    "¡El producto fue registrado exitosamente!": "¡El producto fue registrado exitosamente!",
    "¡Ha ocurrido un error de servidor!": "¡Ha ocurrido un error de servidor!",
    "¡El UID de producto no existe!": "¡El UID de producto no existe!",
    "Kalstein | Diagnosis App": "Kalstein | App de Diagnóstico",
    "Diagnosticar": "Diagnosticar",
    "Registrar Equipo": "Registrar Equipo",
    "Diagnosticando:": "Diagnosticando:",
    "Error 404": "Error 404",
    "La página no existe o fue movida": "La página no existe o fue movida",
    "Diagnosis App": "App de Diagnóstico",
    "Registrate": "Regístrate",
    "Logout": "Cerrar sesión",
    "Registra tu equipo": "Registra tu equipo",
    "Registrar": "Registrar",
    "Tag de usuario no encontrado": "Tag de usuario no encontrado",
    "Nuevo mensaje": "Nuevo mensaje",
    "Enviados": "Enviados",
    "Componer un mensaje": "Componer un mensaje",
    "De:": "De:",
    "Para:": "Para:",
    "Asunto:": "Asunto:",
    "User tag": "User tag",
    "Escribe tu mensaje aquí": "Escribe tu mensaje aquí",
    "Enviar": "Enviar",
    "No hay mensajes": "No hay mensajes",
    "Reply": "Responder",
    "Mensaje no encontrado": "Mensaje no encontrado",
    "ID de mensaje inválido": "ID de mensaje inválido",
    "Quote": "Citar",
    "No data found in your search": "No se encontraron datos en tu búsqueda",
    "Showing results to of results": "Mostrando resultados a de resultados",
    "-18% discount with preorder": "-18% de descuento con preorden",
    "Quantity:": "Cantidad:",
    "Page:": "Página:",
    "Previous": "Anterior",
    "Next": "Siguiente",
    "Categorías de productos": "Categorías de productos",
    "Productos relacionados": "Productos relacionados",
    "Pago Aprobado": "Pago Aprobado",
    "¡Pago Aprobado!": "¡Pago Aprobado!",
    "Su Pago ha sido Aprobado exitosamente.": "Su Pago ha sido Aprobado exitosamente.",
    "Back to Homepage": "Volver a la página principal",
    "Por favor espere...": "Por favor espere...",
    "Falla de servidor": "Falla de servidor",
    "UID invalido": "UID inválido",
    "UID vacio": "UID vacío",
    "Algo ha ido mal": "Algo ha ido mal",
    "Ya se esta ejecutando un diagnostico": "Ya se está ejecutando un diagnóstico",
    "Algunos componentes están fallando": "Algunos componentes están fallando",
    "Todo parece ir correctamente": "Todo parece ir correctamente",
    "Parece que aún no has registrado productos": "Parece que aún no has registrado productos",
    "Ha habido un error de conexión": "Ha habido un error de conexión"
}