{
    "¡Hola! Nos alegra volver a verte.": "Ciao! Siamo felici di rivederti.",
    "Correo electrónico": "E-mail",
    "El correo no es válido": "L'email non è valida",
    "Correo electrónico no registrado": "Email non registrata",
    "Contraseña": "Password",
    "Contraseña incorrecta": "Password errata",
    "¿Olvidaste tu contraseña?": "Hai dimenticato la tua password?",
    "Continuar": "Continua",
    "¿No posees una cuenta?": "Non hai un account?",
    "Registrate": "Registrati",
    "¿No posees una cuenta? Registrate": "Non hai un account? Registrati",
    "Enviar correo para restablecer la contraseña": "Invia e-mail per reimpostare la password",
    "El correo no es válido.": "L'email non è valida.",
    "Enviar correo": "Invia e-mail",
    "Atrás": "Indietro",
    "Error": "Errore",
    "Asistente": "Assistente",
    "Gracias por formar parte de nuestra plataforma Kalstein Francia, ahora ayúdenos a personalizar su perfil según sus necesidades.": "Grazie per far parte della nostra piattaforma Kalstein Francia, ora aiutaci a personalizzare il tuo profilo in base alle tue esigenze.",
    "Nombre": "Nome",
    "Apellido": "Cognome",
    "¿Cómo utilizará nuestra plataforma?": "Come utilizzerai la nostra piattaforma?",
    "Elija una opción": "Scegli un'opzione",
    "Cotizar, comprar o consumir recursos proporcionados por la plataforma": "Richiedi un preventivo, acquista o consuma risorse fornite dalla piattaforma",
    "Anunciar y vender sus productos": "Pubblicizzare e vendere i tuoi prodotti",
    "Impartir conocimientos en el ámbito científico, dar cursos, etc.": "Condividere conoscenze nel campo scientifico, dare corsi, ecc.",
    "Prestación de servicios técnicos": "Fornitura di servizi tecnici",
    "Siguiente": "Avanti",
    "Documento de identidad/pasaporte (opcional)": "Documento d'identità/passaporto (opzionale)",
    "Cargar foto del documento (Opcional)": "Carica foto del documento (Opzionale)",
    "País": "Paese",
    "Teléfono": "Telefono",
    "Dirección": "Indirizzo",
    "Código postal": "Codice postale",
    "Anterior": "Precedente",
    "Finalizar": "Termina",
    "¿Es propietario o pertenece a una empresa?": "Sei proprietario o appartieni a un'azienda?",
    "Si": "Sì",
    "No": "No",
    "Ingeniero": "Ingegnere",
    "Dirección de Ingeniería": "Direzione Ingegneria",
    "Diseñador": "Designer",
    "Compras / Comprador / Finanzas": "Acquisti / Acquirente / Finanze",
    "Gestión de programas y proyectos": "Gestione di programmi e progetti",
    "Operaciones / Gestión de MRO": "Operazioni / Gestione MRO",
    "Liderazgo ejecutivo (CXO, VP, fundador, etc.)": "Leadership esecutivo (CXO, VP, fondatore, ecc.)",
    "Ventas y marketing": "Vendite e marketing",
    "Otros": "Altro",
    "Función": "Ruolo",
    "Documento fiscal (opcional)": "Documento fiscale (opzionale)",
    "Razón social": "Ragione sociale",
    "Estado": "Stato",
    "Dirección fiscal": "Indirizzo fiscale",
    "Sitio web empresarial": "Sito web aziendale",
    "Documento de identidad/Pasaporte": "Documento d'identità/Passaporto",
    "Cargar foto del documento": "Carica foto del documento",
    "or": "o",
    "¿Qué categoría se adapta mejor a tu negocio?": "Quale categoria si adatta meglio alla tua attività?",
    "Fabricante": "Produttore",
    "Distribuidor": "Distributore",
    "Soporte técnico": "Supporto tecnico",
    "Servicios de alquiler y equipos usados": "Servizi di noleggio e attrezzature usate",
    "Científico": "Scientifico",
    "Hola, introduzca su nueva contraseña.": "Ciao, inserisci la tua nuova password.",
    "Nueva contraseña": "Nuova password",
    "Confirmar contraseña": "Conferma password",
    "Su contraseña debe contener:": "La tua password deve contenere:",
    "• Al menos 8 caracteres": "• Almeno 8 caratteri",
    "• Letras minúsculas (a-z)": "• Lettere minuscole (a-z)",
    "• Letras mayúsculas (A-Z)": "• Lettere maiuscole (A-Z)",
    "• Numeros (0-9)": "• Numeri (0-9)",
    "• Caracteres especiales (!@#$%^&*)": "• Caratteri speciali (!@#$%^&*)",
    "Las contraseñas no coinciden.": "Le password non corrispondono.",
    "Cree su cuenta": "Crea il tuo account",
    "Correo disponible": "E-mail disponibile",
    "Este correo electrónico ya está registrado, intente iniciar sesión.": "Questa email è già registrata, prova ad accedere.",
    "Etiqueta de usuario": "Etichetta utente",
    "Your password must containt:": "La tua password deve contenere:",
    "Hemos enviado un correo electrónico a": "Abbiamo inviato un'email a",
    "Guardar": "Salva",
    "Hemos enviado un correo electrónico a con el código de verificación.": "Abbiamo inviato un'email a con il codice di verifica.",
    "con el código de verificación.": "con il codice di verifica.",
    "Verificación de códigos": "Verifica dei codici",
    "El código de validación ha caducado, solicite un nuevo código.": "Il codice di validazione è scaduto, richiedi un nuovo codice.",
    "El código de validación no es válido.": "Il codice di validazione non è valido.",
    "Solicite aquí un nuevo código de validación": "Richiedi qui un nuovo codice di validazione",
    "¿Ya tiene una cuenta?": "Hai già un account?",
    "Iniciar sesión": "Accedi"
}